seq_mealy.v
// Sequence Detector for 10110

module seq_mealy(
    input wire clk, rst,
    input wire X,
    output reg Y
);

parameter IDLE = 3'b000,
          S1 = 3'b001,
          S10 = 3'b010,
          S101 = 3'b011,
          S1011 = 3'b100,
          S10110 = 3'b101;

reg [2:0] state, nxt_state;

always @(posedge clk or posedge rst) begin
    if(rst) begin
        state <= IDLE;
        Y = 1'b0;
    end
    else begin
        state = nxt_state;
        Y = (state == S10110) ? 1'b1 : 1'b0;
    end
end



always @(*) begin
    case (state)

        IDLE : begin
            nxt_state = (X) ? S1 : IDLE;
        end 

        S1 : begin
            nxt_state = (~X) ? S10 : S1;
        end

        S10 : begin
            nxt_state = (X) ? S101 :IDLE;
        end

        S101 : begin
            nxt_state = (X) ? S1011 : S10;
        end

        S1011 : begin
            nxt_state = (~X) ? S10110 : S10;
        end

        S10110 : begin
            nxt_state = (X) ? S101 : IDLE;
        end
        default: begin
            nxt_state = IDLE;
        end
    endcase
end

endmodule

seq_mealy_tb.v
`include "seq_mealy.v"

module tb_seq_mealy;

    // Declare testbench signals
    reg clk, rst, X;
    wire Y;

    // Instantiate the DUT (Device Under Test)
    seq_mealy uut (
        .clk(clk),
        .rst(rst),
        .X(X),
        .Y(Y)
    );

    // Clock generation (50% duty cycle)
    always #5 clk = ~clk;

    // Test sequence
    initial begin
        // Initialize signals
        clk = 0; 
        rst = 1; 
        X = 0;
        #10 rst = 0; // Release reset

        // Input sequence: 1011010 (Overlapping case)
        #10 X = 1;
        #10 X = 0;
        #10 X = 1;
        #10 X = 1;
        #10 X = 0; // Output Y should be 1 here (Detected "10110")
        #10 X = 1;
        #10 X = 1;
        #10 X = 0; // Output Y should be 1 here (Detected "10110")

        #20 $finish;
    end

    // Monitor state transitions
    initial begin
        $monitor("Reset = %b Time=%0t | X=%b | Y=%b ",rst, $time, X, Y);
    end

    // Generate waveform dump for GTKWave
    initial begin
        $dumpfile("waveform.vcd");  // VCD file for GTKWave
        $dumpvars(0, tb_seq_mealy);  // Dump all variables in the module
    end

endmodule

waveform.vcd
$date
	Sun Mar  2 20:03:41 2025
$end
$version
	Icarus Verilog
$end
$timescale
	1s
$end
$scope module tb_seq_mealy $end
$var wire 1 ! Y $end
$var reg 1 " X $end
$var reg 1 # clk $end
$var reg 1 $ rst $end
$scope module uut $end
$var wire 1 " X $end
$var wire 1 # clk $end
$var wire 1 $ rst $end
$var parameter 3 % IDLE $end
$var parameter 3 & S1 $end
$var parameter 3 ' S10 $end
$var parameter 3 ( S101 $end
$var parameter 3 ) S1011 $end
$var parameter 3 * S10110 $end
$var reg 1 ! Y $end
$var reg 3 + nxt_state [2:0] $end
$var reg 3 , state [2:0] $end
$upscope $end
$upscope $end
$enddefinitions $end
$comment Show the parameter values. $end
$dumpall
b101 *
b100 )
b11 (
b10 '
b1 &
b0 %
$end
#0
$dumpvars
b0 ,
b0 +
1$
0#
0"
0!
$end
#5
1#
#10
0#
0$
#15
1#
#20
b1 +
0#
1"
#25
b1 ,
1#
#30
b10 +
0#
0"
#35
b0 +
b10 ,
1#
#40
b11 +
0#
1"
#45
b100 +
b11 ,
1#
#50
0#
#55
b10 +
b100 ,
1#
#60
b101 +
0#
0"
#65
b0 +
1!
b101 ,
1#
#70
b11 +
0#
1"
#75
b100 +
0!
b11 ,
1#
#80
0#
#85
b10 +
b100 ,
1#
#90
b101 +
0#
0"
#95
b0 +
1!
b101 ,
1#
#100
0#
#105
0!
b0 ,
1#
